hermeneus/__init__.py
hermeneus-0.0.1.dist-info/LICENSE
hermeneus-0.0.1.dist-info/METADATA
hermeneus-0.0.1.dist-info/WHEEL
hermeneus-0.0.1.dist-info/top_level.txt
hermeneus-0.0.1.dist-info/RECORD
